filefinder2/__init__.py
filefinder2/_encoding_utils.py
filefinder2/_filefinder2.py
filefinder2/_fileloader2.py
filefinder2/_module_utils.py
filefinder2/_spec_utils.py
filefinder2/_utils.py
filefinder2/_version.py
filefinder2/abc.py
filefinder2/machinery.py
filefinder2/util.py
filefinder2-0.5.0.dist-info/METADATA
filefinder2-0.5.0.dist-info/RECORD
filefinder2-0.5.0.dist-info/WHEEL
filefinder2-0.5.0.dist-info/top_level.txt
